{
  "version": 1,
  "total": 200,
  "totalTests": 1647,
  "items": [
    {
      "id": "two-sum",
      "number": 184,
      "title": "Two Sum",
      "difficulty": "Easy",
      "categories": [
        "Array",
        "Hash Table"
      ],
      "file": "questions/two-sum.json"
    },
    {
      "id": "best-time-to-buy-and-sell-stock",
      "number": 6,
      "title": "Best Time to Buy and Sell Stock",
      "difficulty": "Easy",
      "categories": [
        "Array",
        "Dynamic Programming"
      ],
      "file": "questions/best-time-to-buy-and-sell-stock.json"
    },
    {
      "id": "contains-duplicate",
      "number": 31,
      "title": "Contains Duplicate",
      "difficulty": "Easy",
      "categories": [
        "Array",
        "Hash Table",
        "Sorting"
      ],
      "file": "questions/contains-duplicate.json"
    },
    {
      "id": "valid-anagram",
      "number": 188,
      "title": "Valid Anagram",
      "difficulty": "Easy",
      "categories": [
        "String",
        "Hash Table",
        "Sorting"
      ],
      "file": "questions/valid-anagram.json"
    },
    {
      "id": "valid-parentheses",
      "number": 190,
      "title": "Valid Parentheses",
      "difficulty": "Easy",
      "categories": [
        "String",
        "Stack"
      ],
      "file": "questions/valid-parentheses.json"
    },
    {
      "id": "merge-two-sorted-lists",
      "number": 113,
      "title": "Merge Two Sorted Lists",
      "difficulty": "Easy",
      "categories": [
        "Linked List",
        "Recursion"
      ],
      "file": "questions/merge-two-sorted-lists.json"
    },
    {
      "id": "invert-binary-tree",
      "number": 75,
      "title": "Invert Binary Tree",
      "difficulty": "Easy",
      "categories": [
        "Tree",
        "DFS",
        "BFS",
        "Recursion"
      ],
      "file": "questions/invert-binary-tree.json"
    },
    {
      "id": "binary-search",
      "number": 10,
      "title": "Binary Search",
      "difficulty": "Easy",
      "categories": [
        "Array",
        "Binary Search"
      ],
      "file": "questions/binary-search.json"
    },
    {
      "id": "maximum-subarray",
      "number": 106,
      "title": "Maximum Subarray",
      "difficulty": "Medium",
      "categories": [
        "Array",
        "Dynamic Programming",
        "Divide & Conquer"
      ],
      "file": "questions/maximum-subarray.json"
    },
    {
      "id": "product-of-array-except-self",
      "number": 143,
      "title": "Product of Array Except Self",
      "difficulty": "Medium",
      "categories": [
        "Array",
        "Prefix Sum"
      ],
      "file": "questions/product-of-array-except-self.json"
    },
    {
      "id": "3sum",
      "number": 1,
      "title": "3Sum",
      "difficulty": "Medium",
      "categories": [
        "Array",
        "Two Pointers",
        "Sorting"
      ],
      "file": "questions/3sum.json"
    },
    {
      "id": "longest-substring-without-repeating-characters",
      "number": 98,
      "title": "Longest Substring Without Repeating Characters",
      "difficulty": "Medium",
      "categories": [
        "String",
        "Sliding Window",
        "Hash Table"
      ],
      "file": "questions/longest-substring-without-repeating-characters.json"
    },
    {
      "id": "group-anagrams",
      "number": 64,
      "title": "Group Anagrams",
      "difficulty": "Medium",
      "categories": [
        "String",
        "Hash Table",
        "Sorting"
      ],
      "file": "questions/group-anagrams.json"
    },
    {
      "id": "search-in-rotated-sorted-array",
      "number": 163,
      "title": "Search in Rotated Sorted Array",
      "difficulty": "Medium",
      "categories": [
        "Array",
        "Binary Search"
      ],
      "file": "questions/search-in-rotated-sorted-array.json"
    },
    {
      "id": "number-of-islands",
      "number": 128,
      "title": "Number of Islands",
      "difficulty": "Medium",
      "categories": [
        "Matrix",
        "Graph",
        "DFS",
        "BFS",
        "Union-Find"
      ],
      "file": "questions/number-of-islands.json"
    },
    {
      "id": "course-schedule",
      "number": 38,
      "title": "Course Schedule",
      "difficulty": "Medium",
      "categories": [
        "Graph",
        "BFS",
        "DFS",
        "Topological Sort"
      ],
      "file": "questions/course-schedule.json"
    },
    {
      "id": "coin-change",
      "number": 24,
      "title": "Coin Change",
      "difficulty": "Medium",
      "categories": [
        "Dynamic Programming",
        "Array"
      ],
      "file": "questions/coin-change.json"
    },
    {
      "id": "word-break",
      "number": 195,
      "title": "Word Break",
      "difficulty": "Medium",
      "categories": [
        "Dynamic Programming",
        "String",
        "Hash Table",
        "Trie"
      ],
      "file": "questions/word-break.json"
    },
    {
      "id": "top-k-frequent-elements",
      "number": 182,
      "title": "Top K Frequent Elements",
      "difficulty": "Medium",
      "categories": [
        "Array",
        "Hash Table",
        "Heap / Priority Queue",
        "Sorting"
      ],
      "file": "questions/top-k-frequent-elements.json"
    },
    {
      "id": "trapping-rain-water",
      "number": 183,
      "title": "Trapping Rain Water",
      "difficulty": "Hard",
      "categories": [
        "Array",
        "Two Pointers",
        "Stack",
        "Dynamic Programming",
        "Monotonic Stack"
      ],
      "file": "questions/trapping-rain-water.json"
    },
    {
      "id": "valid-palindrome",
      "number": 189,
      "title": "Valid Palindrome",
      "difficulty": "Easy",
      "categories": [
        "Two Pointers",
        "String"
      ],
      "file": "questions/valid-palindrome.json"
    },
    {
      "id": "two-sum-ii",
      "number": 185,
      "title": "Two Sum II - Input Array Is Sorted",
      "difficulty": "Medium",
      "categories": [
        "Two Pointers",
        "Binary Search",
        "Array"
      ],
      "file": "questions/two-sum-ii.json"
    },
    {
      "id": "container-with-most-water",
      "number": 30,
      "title": "Container With Most Water",
      "difficulty": "Medium",
      "categories": [
        "Two Pointers",
        "Greedy",
        "Array"
      ],
      "file": "questions/container-with-most-water.json"
    },
    {
      "id": "move-zeroes",
      "number": 121,
      "title": "Move Zeroes",
      "difficulty": "Easy",
      "categories": [
        "Two Pointers",
        "Array"
      ],
      "file": "questions/move-zeroes.json"
    },
    {
      "id": "remove-duplicates-from-sorted-array",
      "number": 148,
      "title": "Remove Duplicates from Sorted Array",
      "difficulty": "Easy",
      "categories": [
        "Two Pointers",
        "Array"
      ],
      "file": "questions/remove-duplicates-from-sorted-array.json"
    },
    {
      "id": "merge-sorted-array",
      "number": 111,
      "title": "Merge Sorted Array",
      "difficulty": "Easy",
      "categories": [
        "Two Pointers",
        "Array"
      ],
      "file": "questions/merge-sorted-array.json"
    },
    {
      "id": "longest-consecutive-sequence",
      "number": 93,
      "title": "Longest Consecutive Sequence",
      "difficulty": "Medium",
      "categories": [
        "Hash Table",
        "Union-Find",
        "Array"
      ],
      "file": "questions/longest-consecutive-sequence.json"
    },
    {
      "id": "encode-decode-strings",
      "number": 49,
      "title": "Encode and Decode Strings",
      "difficulty": "Medium",
      "categories": [
        "String",
        "Design"
      ],
      "file": "questions/encode-decode-strings.json"
    },
    {
      "id": "longest-palindromic-substring",
      "number": 96,
      "title": "Longest Palindromic Substring",
      "difficulty": "Medium",
      "categories": [
        "Two Pointers",
        "String",
        "Dynamic Programming"
      ],
      "file": "questions/longest-palindromic-substring.json"
    },
    {
      "id": "palindromic-substrings",
      "number": 133,
      "title": "Palindromic Substrings",
      "difficulty": "Medium",
      "categories": [
        "String",
        "Dynamic Programming"
      ],
      "file": "questions/palindromic-substrings.json"
    },
    {
      "id": "longest-repeating-character-replacement",
      "number": 97,
      "title": "Longest Repeating Character Replacement",
      "difficulty": "Medium",
      "categories": [
        "Sliding Window",
        "Hash Table",
        "String"
      ],
      "file": "questions/longest-repeating-character-replacement.json"
    },
    {
      "id": "minimum-window-substring",
      "number": 119,
      "title": "Minimum Window Substring",
      "difficulty": "Hard",
      "categories": [
        "Sliding Window",
        "Hash Table",
        "String"
      ],
      "file": "questions/minimum-window-substring.json"
    },
    {
      "id": "permutation-in-string",
      "number": 137,
      "title": "Permutation in String",
      "difficulty": "Medium",
      "categories": [
        "Sliding Window",
        "Hash Table",
        "String"
      ],
      "file": "questions/permutation-in-string.json"
    },
    {
      "id": "sliding-window-maximum",
      "number": 168,
      "title": "Sliding Window Maximum",
      "difficulty": "Hard",
      "categories": [
        "Sliding Window",
        "Heap / Priority Queue",
        "Queue",
        "Monotonic Stack",
        "Array"
      ],
      "file": "questions/sliding-window-maximum.json"
    },
    {
      "id": "find-minimum-in-rotated-sorted-array",
      "number": 55,
      "title": "Find Minimum in Rotated Sorted Array",
      "difficulty": "Medium",
      "categories": [
        "Binary Search",
        "Array"
      ],
      "file": "questions/find-minimum-in-rotated-sorted-array.json"
    },
    {
      "id": "search-2d-matrix",
      "number": 162,
      "title": "Search a 2D Matrix",
      "difficulty": "Medium",
      "categories": [
        "Binary Search",
        "Matrix",
        "Array"
      ],
      "file": "questions/search-2d-matrix.json"
    },
    {
      "id": "koko-eating-bananas",
      "number": 80,
      "title": "Koko Eating Bananas",
      "difficulty": "Medium",
      "categories": [
        "Binary Search",
        "Array"
      ],
      "file": "questions/koko-eating-bananas.json"
    },
    {
      "id": "min-stack",
      "number": 115,
      "title": "Min Stack",
      "difficulty": "Medium",
      "categories": [
        "Stack",
        "Design"
      ],
      "file": "questions/min-stack.json"
    },
    {
      "id": "evaluate-reverse-polish-notation",
      "number": 50,
      "title": "Evaluate Reverse Polish Notation",
      "difficulty": "Medium",
      "categories": [
        "Stack",
        "Math"
      ],
      "file": "questions/evaluate-reverse-polish-notation.json"
    },
    {
      "id": "daily-temperatures",
      "number": 40,
      "title": "Daily Temperatures",
      "difficulty": "Medium",
      "categories": [
        "Stack",
        "Monotonic Stack",
        "Array"
      ],
      "file": "questions/daily-temperatures.json"
    },
    {
      "id": "largest-rectangle-in-histogram",
      "number": 84,
      "title": "Largest Rectangle in Histogram",
      "difficulty": "Hard",
      "categories": [
        "Stack",
        "Monotonic Stack",
        "Array"
      ],
      "file": "questions/largest-rectangle-in-histogram.json"
    },
    {
      "id": "generate-parentheses",
      "number": 62,
      "title": "Generate Parentheses",
      "difficulty": "Medium",
      "categories": [
        "Backtracking",
        "Dynamic Programming",
        "String"
      ],
      "file": "questions/generate-parentheses.json"
    },
    {
      "id": "car-fleet",
      "number": 20,
      "title": "Car Fleet",
      "difficulty": "Medium",
      "categories": [
        "Stack",
        "Monotonic Stack",
        "Sorting",
        "Greedy"
      ],
      "file": "questions/car-fleet.json"
    },
    {
      "id": "squares-of-a-sorted-array",
      "number": 171,
      "title": "Squares of a Sorted Array",
      "difficulty": "Easy",
      "categories": [
        "Two Pointers",
        "Sorting",
        "Array"
      ],
      "file": "questions/squares-of-a-sorted-array.json"
    },
    {
      "id": "set-matrix-zeroes",
      "number": 165,
      "title": "Set Matrix Zeroes",
      "difficulty": "Medium",
      "categories": [
        "Matrix",
        "Array",
        "Hash Table"
      ],
      "file": "questions/set-matrix-zeroes.json"
    },
    {
      "id": "reverse-linked-list",
      "number": 154,
      "title": "Reverse Linked List",
      "difficulty": "Easy",
      "categories": [
        "Linked List",
        "Recursion"
      ],
      "file": "questions/reverse-linked-list.json"
    },
    {
      "id": "linked-list-cycle",
      "number": 89,
      "title": "Linked List Cycle",
      "difficulty": "Easy",
      "categories": [
        "Linked List",
        "Two Pointers",
        "Hash Table"
      ],
      "file": "questions/linked-list-cycle.json"
    },
    {
      "id": "linked-list-cycle-ii",
      "number": 90,
      "title": "Linked List Cycle II",
      "difficulty": "Medium",
      "categories": [
        "Linked List",
        "Two Pointers",
        "Hash Table"
      ],
      "file": "questions/linked-list-cycle-ii.json"
    },
    {
      "id": "middle-of-the-linked-list",
      "number": 114,
      "title": "Middle of the Linked List",
      "difficulty": "Easy",
      "categories": [
        "Linked List",
        "Two Pointers"
      ],
      "file": "questions/middle-of-the-linked-list.json"
    },
    {
      "id": "palindrome-linked-list",
      "number": 130,
      "title": "Palindrome Linked List",
      "difficulty": "Easy",
      "categories": [
        "Linked List",
        "Two Pointers",
        "Stack",
        "Recursion"
      ],
      "file": "questions/palindrome-linked-list.json"
    },
    {
      "id": "remove-nth-node-from-end-of-list",
      "number": 149,
      "title": "Remove Nth Node From End of List",
      "difficulty": "Medium",
      "categories": [
        "Linked List",
        "Two Pointers"
      ],
      "file": "questions/remove-nth-node-from-end-of-list.json"
    },
    {
      "id": "reorder-list",
      "number": 150,
      "title": "Reorder List",
      "difficulty": "Medium",
      "categories": [
        "Linked List",
        "Two Pointers",
        "Stack"
      ],
      "file": "questions/reorder-list.json"
    },
    {
      "id": "add-two-numbers",
      "number": 3,
      "title": "Add Two Numbers",
      "difficulty": "Medium",
      "categories": [
        "Linked List",
        "Math",
        "Recursion"
      ],
      "file": "questions/add-two-numbers.json"
    },
    {
      "id": "copy-list-with-random-pointer",
      "number": 34,
      "title": "Copy List with Random Pointer",
      "difficulty": "Medium",
      "categories": [
        "Linked List",
        "Hash Table"
      ],
      "file": "questions/copy-list-with-random-pointer.json"
    },
    {
      "id": "merge-k-sorted-lists",
      "number": 110,
      "title": "Merge k Sorted Lists",
      "difficulty": "Hard",
      "categories": [
        "Linked List",
        "Heap / Priority Queue",
        "Divide & Conquer"
      ],
      "file": "questions/merge-k-sorted-lists.json"
    },
    {
      "id": "reverse-nodes-in-k-group",
      "number": 155,
      "title": "Reverse Nodes in k-Group",
      "difficulty": "Hard",
      "categories": [
        "Linked List",
        "Recursion"
      ],
      "file": "questions/reverse-nodes-in-k-group.json"
    },
    {
      "id": "lru-cache",
      "number": 101,
      "title": "LRU Cache",
      "difficulty": "Medium",
      "categories": [
        "Hash Table",
        "Linked List",
        "Design"
      ],
      "file": "questions/lru-cache.json"
    },
    {
      "id": "maximum-depth-of-binary-tree",
      "number": 104,
      "title": "Maximum Depth of Binary Tree",
      "difficulty": "Easy",
      "categories": [
        "Tree",
        "DFS",
        "BFS",
        "Recursion"
      ],
      "file": "questions/maximum-depth-of-binary-tree.json"
    },
    {
      "id": "same-tree",
      "number": 161,
      "title": "Same Tree",
      "difficulty": "Easy",
      "categories": [
        "Tree",
        "DFS",
        "BFS"
      ],
      "file": "questions/same-tree.json"
    },
    {
      "id": "symmetric-tree",
      "number": 178,
      "title": "Symmetric Tree",
      "difficulty": "Easy",
      "categories": [
        "Tree",
        "DFS",
        "BFS"
      ],
      "file": "questions/symmetric-tree.json"
    },
    {
      "id": "diameter-of-binary-tree",
      "number": 46,
      "title": "Diameter of Binary Tree",
      "difficulty": "Easy",
      "categories": [
        "Tree",
        "DFS"
      ],
      "file": "questions/diameter-of-binary-tree.json"
    },
    {
      "id": "balanced-binary-tree",
      "number": 5,
      "title": "Balanced Binary Tree",
      "difficulty": "Easy",
      "categories": [
        "Tree",
        "DFS"
      ],
      "file": "questions/balanced-binary-tree.json"
    },
    {
      "id": "path-sum",
      "number": 136,
      "title": "Path Sum",
      "difficulty": "Easy",
      "categories": [
        "Tree",
        "DFS",
        "BFS"
      ],
      "file": "questions/path-sum.json"
    },
    {
      "id": "binary-tree-inorder-traversal",
      "number": 11,
      "title": "Binary Tree Inorder Traversal",
      "difficulty": "Easy",
      "categories": [
        "Tree",
        "DFS",
        "Stack"
      ],
      "file": "questions/binary-tree-inorder-traversal.json"
    },
    {
      "id": "subtree-of-another-tree",
      "number": 175,
      "title": "Subtree of Another Tree",
      "difficulty": "Easy",
      "categories": [
        "Tree",
        "DFS",
        "String"
      ],
      "file": "questions/subtree-of-another-tree.json"
    },
    {
      "id": "binary-tree-level-order-traversal",
      "number": 12,
      "title": "Binary Tree Level Order Traversal",
      "difficulty": "Medium",
      "categories": [
        "Tree",
        "BFS"
      ],
      "file": "questions/binary-tree-level-order-traversal.json"
    },
    {
      "id": "binary-tree-right-side-view",
      "number": 14,
      "title": "Binary Tree Right Side View",
      "difficulty": "Medium",
      "categories": [
        "Tree",
        "BFS",
        "DFS"
      ],
      "file": "questions/binary-tree-right-side-view.json"
    },
    {
      "id": "binary-tree-zigzag-level-order-traversal",
      "number": 15,
      "title": "Binary Tree Zigzag Level Order Traversal",
      "difficulty": "Medium",
      "categories": [
        "Tree",
        "BFS"
      ],
      "file": "questions/binary-tree-zigzag-level-order-traversal.json"
    },
    {
      "id": "count-good-nodes-in-binary-tree",
      "number": 35,
      "title": "Count Good Nodes in Binary Tree",
      "difficulty": "Medium",
      "categories": [
        "Tree",
        "DFS",
        "BFS"
      ],
      "file": "questions/count-good-nodes-in-binary-tree.json"
    },
    {
      "id": "validate-binary-search-tree",
      "number": 193,
      "title": "Validate Binary Search Tree",
      "difficulty": "Medium",
      "categories": [
        "Tree",
        "DFS",
        "Binary Search Tree"
      ],
      "file": "questions/validate-binary-search-tree.json"
    },
    {
      "id": "kth-smallest-element-in-a-bst",
      "number": 83,
      "title": "Kth Smallest Element in a BST",
      "difficulty": "Medium",
      "categories": [
        "Tree",
        "Binary Search Tree",
        "DFS"
      ],
      "file": "questions/kth-smallest-element-in-a-bst.json"
    },
    {
      "id": "lowest-common-ancestor-of-a-bst",
      "number": 100,
      "title": "Lowest Common Ancestor of a Binary Search Tree",
      "difficulty": "Medium",
      "categories": [
        "Tree",
        "Binary Search Tree",
        "DFS"
      ],
      "file": "questions/lowest-common-ancestor-of-a-bst.json"
    },
    {
      "id": "lowest-common-ancestor-of-a-binary-tree",
      "number": 99,
      "title": "Lowest Common Ancestor of a Binary Tree",
      "difficulty": "Medium",
      "categories": [
        "Tree",
        "DFS"
      ],
      "file": "questions/lowest-common-ancestor-of-a-binary-tree.json"
    },
    {
      "id": "construct-binary-tree-from-preorder-and-inorder",
      "number": 29,
      "title": "Construct Binary Tree from Preorder and Inorder Traversal",
      "difficulty": "Medium",
      "categories": [
        "Tree",
        "DFS",
        "Hash Table",
        "Divide & Conquer"
      ],
      "file": "questions/construct-binary-tree-from-preorder-and-inorder.json"
    },
    {
      "id": "binary-tree-maximum-path-sum",
      "number": 13,
      "title": "Binary Tree Maximum Path Sum",
      "difficulty": "Hard",
      "categories": [
        "Tree",
        "DFS",
        "Dynamic Programming"
      ],
      "file": "questions/binary-tree-maximum-path-sum.json"
    },
    {
      "id": "serialize-and-deserialize-binary-tree",
      "number": 164,
      "title": "Serialize and Deserialize Binary Tree",
      "difficulty": "Hard",
      "categories": [
        "Tree",
        "DFS",
        "BFS",
        "Design",
        "String"
      ],
      "file": "questions/serialize-and-deserialize-binary-tree.json"
    },
    {
      "id": "convert-sorted-array-to-bst",
      "number": 33,
      "title": "Convert Sorted Array to Binary Search Tree",
      "difficulty": "Easy",
      "categories": [
        "Tree",
        "Binary Search Tree",
        "Divide & Conquer"
      ],
      "file": "questions/convert-sorted-array-to-bst.json"
    },
    {
      "id": "clone-graph",
      "number": 23,
      "title": "Clone Graph",
      "difficulty": "Medium",
      "categories": [
        "Graph",
        "BFS",
        "DFS",
        "Hash Table"
      ],
      "file": "questions/clone-graph.json"
    },
    {
      "id": "pacific-atlantic-water-flow",
      "number": 129,
      "title": "Pacific Atlantic Water Flow",
      "difficulty": "Medium",
      "categories": [
        "Matrix",
        "BFS",
        "DFS"
      ],
      "file": "questions/pacific-atlantic-water-flow.json"
    },
    {
      "id": "course-schedule-ii",
      "number": 39,
      "title": "Course Schedule II",
      "difficulty": "Medium",
      "categories": [
        "Graph",
        "Topological Sort",
        "BFS",
        "DFS"
      ],
      "file": "questions/course-schedule-ii.json"
    },
    {
      "id": "number-of-connected-components",
      "number": 127,
      "title": "Number of Connected Components in an Undirected Graph",
      "difficulty": "Medium",
      "categories": [
        "Graph",
        "Union-Find",
        "DFS",
        "BFS"
      ],
      "file": "questions/number-of-connected-components.json"
    },
    {
      "id": "graph-valid-tree",
      "number": 63,
      "title": "Graph Valid Tree",
      "difficulty": "Medium",
      "categories": [
        "Graph",
        "Union-Find",
        "DFS",
        "BFS"
      ],
      "file": "questions/graph-valid-tree.json"
    },
    {
      "id": "word-ladder",
      "number": 196,
      "title": "Word Ladder",
      "difficulty": "Hard",
      "categories": [
        "Graph",
        "BFS",
        "String",
        "Hash Table"
      ],
      "file": "questions/word-ladder.json"
    },
    {
      "id": "rotting-oranges",
      "number": 160,
      "title": "Rotting Oranges",
      "difficulty": "Medium",
      "categories": [
        "Matrix",
        "BFS"
      ],
      "file": "questions/rotting-oranges.json"
    },
    {
      "id": "surrounded-regions",
      "number": 177,
      "title": "Surrounded Regions",
      "difficulty": "Medium",
      "categories": [
        "Matrix",
        "DFS",
        "BFS",
        "Union-Find"
      ],
      "file": "questions/surrounded-regions.json"
    },
    {
      "id": "walls-and-gates",
      "number": 194,
      "title": "Walls and Gates",
      "difficulty": "Medium",
      "categories": [
        "Matrix",
        "BFS"
      ],
      "file": "questions/walls-and-gates.json"
    },
    {
      "id": "max-area-of-island",
      "number": 103,
      "title": "Max Area of Island",
      "difficulty": "Medium",
      "categories": [
        "Matrix",
        "DFS",
        "BFS"
      ],
      "file": "questions/max-area-of-island.json"
    },
    {
      "id": "redundant-connection",
      "number": 146,
      "title": "Redundant Connection",
      "difficulty": "Medium",
      "categories": [
        "Graph",
        "Union-Find"
      ],
      "file": "questions/redundant-connection.json"
    },
    {
      "id": "network-delay-time",
      "number": 124,
      "title": "Network Delay Time",
      "difficulty": "Medium",
      "categories": [
        "Graph",
        "Heap / Priority Queue",
        "Shortest Path"
      ],
      "file": "questions/network-delay-time.json"
    },
    {
      "id": "cheapest-flights-within-k-stops",
      "number": 21,
      "title": "Cheapest Flights Within K Stops",
      "difficulty": "Medium",
      "categories": [
        "Graph",
        "Shortest Path",
        "Dynamic Programming",
        "BFS"
      ],
      "file": "questions/cheapest-flights-within-k-stops.json"
    },
    {
      "id": "reconstruct-itinerary",
      "number": 145,
      "title": "Reconstruct Itinerary",
      "difficulty": "Hard",
      "categories": [
        "Graph",
        "DFS",
        "Eulerian Path"
      ],
      "file": "questions/reconstruct-itinerary.json"
    },
    {
      "id": "alien-dictionary",
      "number": 4,
      "title": "Alien Dictionary",
      "difficulty": "Hard",
      "categories": [
        "Graph",
        "Topological Sort",
        "String"
      ],
      "file": "questions/alien-dictionary.json"
    },
    {
      "id": "kth-largest-element-in-an-array",
      "number": 82,
      "title": "Kth Largest Element in an Array",
      "difficulty": "Medium",
      "categories": [
        "Array",
        "Heap / Priority Queue",
        "Divide & Conquer",
        "Sorting"
      ],
      "file": "questions/kth-largest-element-in-an-array.json"
    },
    {
      "id": "kth-largest-element-in-a-stream",
      "number": 81,
      "title": "Kth Largest Element in a Stream",
      "difficulty": "Easy",
      "categories": [
        "Heap / Priority Queue",
        "Design",
        "Data Stream"
      ],
      "file": "questions/kth-largest-element-in-a-stream.json"
    },
    {
      "id": "k-closest-points-to-origin",
      "number": 79,
      "title": "K Closest Points to Origin",
      "difficulty": "Medium",
      "categories": [
        "Array",
        "Heap / Priority Queue",
        "Math",
        "Divide & Conquer",
        "Sorting"
      ],
      "file": "questions/k-closest-points-to-origin.json"
    },
    {
      "id": "last-stone-weight",
      "number": 85,
      "title": "Last Stone Weight",
      "difficulty": "Easy",
      "categories": [
        "Array",
        "Heap / Priority Queue"
      ],
      "file": "questions/last-stone-weight.json"
    },
    {
      "id": "task-scheduler",
      "number": 180,
      "title": "Task Scheduler",
      "difficulty": "Medium",
      "categories": [
        "Array",
        "Hash Table",
        "Heap / Priority Queue",
        "Greedy"
      ],
      "file": "questions/task-scheduler.json"
    },
    {
      "id": "find-median-from-data-stream",
      "number": 54,
      "title": "Find Median from Data Stream",
      "difficulty": "Hard",
      "categories": [
        "Heap / Priority Queue",
        "Design",
        "Data Stream"
      ],
      "file": "questions/find-median-from-data-stream.json"
    },
    {
      "id": "implement-trie",
      "number": 70,
      "title": "Implement Trie (Prefix Tree)",
      "difficulty": "Medium",
      "categories": [
        "String",
        "Trie",
        "Hash Table",
        "Design"
      ],
      "file": "questions/implement-trie.json"
    },
    {
      "id": "design-add-and-search-words-data-structure",
      "number": 42,
      "title": "Design Add and Search Words Data Structure",
      "difficulty": "Medium",
      "categories": [
        "String",
        "Trie",
        "DFS",
        "Design"
      ],
      "file": "questions/design-add-and-search-words-data-structure.json"
    },
    {
      "id": "word-search-ii",
      "number": 199,
      "title": "Word Search II",
      "difficulty": "Hard",
      "categories": [
        "Array",
        "String",
        "Trie",
        "Backtracking",
        "Matrix"
      ],
      "file": "questions/word-search-ii.json"
    },
    {
      "id": "reorganize-string",
      "number": 151,
      "title": "Reorganize String",
      "difficulty": "Medium",
      "categories": [
        "String",
        "Hash Table",
        "Heap / Priority Queue",
        "Greedy",
        "Sorting"
      ],
      "file": "questions/reorganize-string.json"
    },
    {
      "id": "climbing-stairs",
      "number": 22,
      "title": "Climbing Stairs",
      "difficulty": "Easy",
      "categories": [
        "Dynamic Programming",
        "Math",
        "Memoization"
      ],
      "file": "questions/climbing-stairs.json"
    },
    {
      "id": "house-robber",
      "number": 68,
      "title": "House Robber",
      "difficulty": "Medium",
      "categories": [
        "Array",
        "Dynamic Programming"
      ],
      "file": "questions/house-robber.json"
    },
    {
      "id": "house-robber-ii",
      "number": 69,
      "title": "House Robber II",
      "difficulty": "Medium",
      "categories": [
        "Array",
        "Dynamic Programming"
      ],
      "file": "questions/house-robber-ii.json"
    },
    {
      "id": "decode-ways",
      "number": 41,
      "title": "Decode Ways",
      "difficulty": "Medium",
      "categories": [
        "String",
        "Dynamic Programming"
      ],
      "file": "questions/decode-ways.json"
    },
    {
      "id": "maximum-product-subarray",
      "number": 105,
      "title": "Maximum Product Subarray",
      "difficulty": "Medium",
      "categories": [
        "Array",
        "Dynamic Programming"
      ],
      "file": "questions/maximum-product-subarray.json"
    },
    {
      "id": "longest-increasing-subsequence",
      "number": 95,
      "title": "Longest Increasing Subsequence",
      "difficulty": "Medium",
      "categories": [
        "Array",
        "Binary Search",
        "Dynamic Programming"
      ],
      "file": "questions/longest-increasing-subsequence.json"
    },
    {
      "id": "partition-equal-subset-sum",
      "number": 134,
      "title": "Partition Equal Subset Sum",
      "difficulty": "Medium",
      "categories": [
        "Array",
        "Dynamic Programming"
      ],
      "file": "questions/partition-equal-subset-sum.json"
    },
    {
      "id": "unique-paths",
      "number": 186,
      "title": "Unique Paths",
      "difficulty": "Medium",
      "categories": [
        "Math",
        "Dynamic Programming",
        "Combinatorics"
      ],
      "file": "questions/unique-paths.json"
    },
    {
      "id": "unique-paths-ii",
      "number": 187,
      "title": "Unique Paths II",
      "difficulty": "Medium",
      "categories": [
        "Array",
        "Dynamic Programming",
        "Matrix"
      ],
      "file": "questions/unique-paths-ii.json"
    },
    {
      "id": "minimum-path-sum",
      "number": 118,
      "title": "Minimum Path Sum",
      "difficulty": "Medium",
      "categories": [
        "Array",
        "Dynamic Programming",
        "Matrix"
      ],
      "file": "questions/minimum-path-sum.json"
    },
    {
      "id": "jump-game",
      "number": 77,
      "title": "Jump Game",
      "difficulty": "Medium",
      "categories": [
        "Array",
        "Dynamic Programming",
        "Greedy"
      ],
      "file": "questions/jump-game.json"
    },
    {
      "id": "jump-game-ii",
      "number": 78,
      "title": "Jump Game II",
      "difficulty": "Medium",
      "categories": [
        "Array",
        "Dynamic Programming",
        "Greedy",
        "BFS"
      ],
      "file": "questions/jump-game-ii.json"
    },
    {
      "id": "coin-change-ii",
      "number": 25,
      "title": "Coin Change II",
      "difficulty": "Medium",
      "categories": [
        "Array",
        "Dynamic Programming"
      ],
      "file": "questions/coin-change-ii.json"
    },
    {
      "id": "combination-sum-iv",
      "number": 28,
      "title": "Combination Sum IV",
      "difficulty": "Medium",
      "categories": [
        "Array",
        "Dynamic Programming"
      ],
      "file": "questions/combination-sum-iv.json"
    },
    {
      "id": "target-sum",
      "number": 179,
      "title": "Target Sum",
      "difficulty": "Medium",
      "categories": [
        "Array",
        "Dynamic Programming",
        "Backtracking"
      ],
      "file": "questions/target-sum.json"
    },
    {
      "id": "longest-common-subsequence",
      "number": 92,
      "title": "Longest Common Subsequence",
      "difficulty": "Medium",
      "categories": [
        "String",
        "Dynamic Programming"
      ],
      "file": "questions/longest-common-subsequence.json"
    },
    {
      "id": "best-time-to-buy-and-sell-stock-with-cooldown",
      "number": 9,
      "title": "Best Time to Buy and Sell Stock with Cooldown",
      "difficulty": "Medium",
      "categories": [
        "Array",
        "Dynamic Programming"
      ],
      "file": "questions/best-time-to-buy-and-sell-stock-with-cooldown.json"
    },
    {
      "id": "best-time-to-buy-and-sell-stock-iv",
      "number": 8,
      "title": "Best Time to Buy and Sell Stock IV",
      "difficulty": "Hard",
      "categories": [
        "Array",
        "Dynamic Programming"
      ],
      "file": "questions/best-time-to-buy-and-sell-stock-iv.json"
    },
    {
      "id": "edit-distance",
      "number": 48,
      "title": "Edit Distance",
      "difficulty": "Medium",
      "categories": [
        "String",
        "Dynamic Programming"
      ],
      "file": "questions/edit-distance.json"
    },
    {
      "id": "burst-balloons",
      "number": 18,
      "title": "Burst Balloons",
      "difficulty": "Hard",
      "categories": [
        "Array",
        "Dynamic Programming"
      ],
      "file": "questions/burst-balloons.json"
    },
    {
      "id": "regular-expression-matching",
      "number": 147,
      "title": "Regular Expression Matching",
      "difficulty": "Hard",
      "categories": [
        "String",
        "Dynamic Programming",
        "Recursion"
      ],
      "file": "questions/regular-expression-matching.json"
    },
    {
      "id": "interleaving-string",
      "number": 74,
      "title": "Interleaving String",
      "difficulty": "Medium",
      "categories": [
        "String",
        "Dynamic Programming"
      ],
      "file": "questions/interleaving-string.json"
    },
    {
      "id": "longest-increasing-path-in-a-matrix",
      "number": 94,
      "title": "Longest Increasing Path in a Matrix",
      "difficulty": "Hard",
      "categories": [
        "Array",
        "Dynamic Programming",
        "DFS",
        "Memoization",
        "Matrix",
        "Topological Sort"
      ],
      "file": "questions/longest-increasing-path-in-a-matrix.json"
    },
    {
      "id": "subsets",
      "number": 173,
      "title": "Subsets",
      "difficulty": "Medium",
      "categories": [
        "Array",
        "Backtracking",
        "Bit Manipulation"
      ],
      "file": "questions/subsets.json"
    },
    {
      "id": "subsets-ii",
      "number": 174,
      "title": "Subsets II",
      "difficulty": "Medium",
      "categories": [
        "Array",
        "Backtracking",
        "Bit Manipulation"
      ],
      "file": "questions/subsets-ii.json"
    },
    {
      "id": "permutations",
      "number": 138,
      "title": "Permutations",
      "difficulty": "Medium",
      "categories": [
        "Array",
        "Backtracking"
      ],
      "file": "questions/permutations.json"
    },
    {
      "id": "permutations-ii",
      "number": 139,
      "title": "Permutations II",
      "difficulty": "Medium",
      "categories": [
        "Array",
        "Backtracking"
      ],
      "file": "questions/permutations-ii.json"
    },
    {
      "id": "combination-sum",
      "number": 26,
      "title": "Combination Sum",
      "difficulty": "Medium",
      "categories": [
        "Array",
        "Backtracking"
      ],
      "file": "questions/combination-sum.json"
    },
    {
      "id": "combination-sum-ii",
      "number": 27,
      "title": "Combination Sum II",
      "difficulty": "Medium",
      "categories": [
        "Array",
        "Backtracking"
      ],
      "file": "questions/combination-sum-ii.json"
    },
    {
      "id": "word-search",
      "number": 198,
      "title": "Word Search",
      "difficulty": "Medium",
      "categories": [
        "Array",
        "String",
        "Backtracking",
        "Matrix"
      ],
      "file": "questions/word-search.json"
    },
    {
      "id": "palindrome-partitioning",
      "number": 132,
      "title": "Palindrome Partitioning",
      "difficulty": "Medium",
      "categories": [
        "String",
        "Backtracking",
        "Dynamic Programming"
      ],
      "file": "questions/palindrome-partitioning.json"
    },
    {
      "id": "n-queens",
      "number": 123,
      "title": "N-Queens",
      "difficulty": "Hard",
      "categories": [
        "Array",
        "Backtracking"
      ],
      "file": "questions/n-queens.json"
    },
    {
      "id": "letter-combinations-of-a-phone-number",
      "number": 87,
      "title": "Letter Combinations of a Phone Number",
      "difficulty": "Medium",
      "categories": [
        "Hash Table",
        "String",
        "Backtracking"
      ],
      "file": "questions/letter-combinations-of-a-phone-number.json"
    },
    {
      "id": "insert-interval",
      "number": 72,
      "title": "Insert Interval",
      "difficulty": "Medium",
      "categories": [
        "Array",
        "Intervals"
      ],
      "file": "questions/insert-interval.json"
    },
    {
      "id": "merge-intervals",
      "number": 109,
      "title": "Merge Intervals",
      "difficulty": "Medium",
      "categories": [
        "Array",
        "Sorting",
        "Intervals"
      ],
      "file": "questions/merge-intervals.json"
    },
    {
      "id": "non-overlapping-intervals",
      "number": 125,
      "title": "Non-overlapping Intervals",
      "difficulty": "Medium",
      "categories": [
        "Array",
        "Greedy",
        "Intervals",
        "Sorting",
        "Dynamic Programming"
      ],
      "file": "questions/non-overlapping-intervals.json"
    },
    {
      "id": "meeting-rooms",
      "number": 107,
      "title": "Meeting Rooms",
      "difficulty": "Easy",
      "categories": [
        "Array",
        "Sorting",
        "Intervals"
      ],
      "file": "questions/meeting-rooms.json"
    },
    {
      "id": "meeting-rooms-ii",
      "number": 108,
      "title": "Meeting Rooms II",
      "difficulty": "Medium",
      "categories": [
        "Array",
        "Sorting",
        "Heap / Priority Queue",
        "Intervals"
      ],
      "file": "questions/meeting-rooms-ii.json"
    },
    {
      "id": "minimum-number-of-arrows-to-burst-balloons",
      "number": 117,
      "title": "Minimum Number of Arrows to Burst Balloons",
      "difficulty": "Medium",
      "categories": [
        "Array",
        "Greedy",
        "Sorting",
        "Intervals"
      ],
      "file": "questions/minimum-number-of-arrows-to-burst-balloons.json"
    },
    {
      "id": "best-time-to-buy-and-sell-stock-ii",
      "number": 7,
      "title": "Best Time to Buy and Sell Stock II",
      "difficulty": "Medium",
      "categories": [
        "Array",
        "Greedy",
        "Dynamic Programming"
      ],
      "file": "questions/best-time-to-buy-and-sell-stock-ii.json"
    },
    {
      "id": "gas-station",
      "number": 61,
      "title": "Gas Station",
      "difficulty": "Medium",
      "categories": [
        "Array",
        "Greedy"
      ],
      "file": "questions/gas-station.json"
    },
    {
      "id": "hand-of-straights",
      "number": 66,
      "title": "Hand of Straights",
      "difficulty": "Medium",
      "categories": [
        "Array",
        "Hash Table",
        "Sorting",
        "Greedy"
      ],
      "file": "questions/hand-of-straights.json"
    },
    {
      "id": "merge-triplets-to-form-target-triplet",
      "number": 112,
      "title": "Merge Triplets to Form Target Triplet",
      "difficulty": "Medium",
      "categories": [
        "Array",
        "Greedy"
      ],
      "file": "questions/merge-triplets-to-form-target-triplet.json"
    },
    {
      "id": "partition-labels",
      "number": 135,
      "title": "Partition Labels",
      "difficulty": "Medium",
      "categories": [
        "String",
        "Hash Table",
        "Two Pointers",
        "Greedy"
      ],
      "file": "questions/partition-labels.json"
    },
    {
      "id": "valid-parenthesis-string",
      "number": 191,
      "title": "Valid Parenthesis String",
      "difficulty": "Medium",
      "categories": [
        "String",
        "Stack",
        "Greedy",
        "Dynamic Programming"
      ],
      "file": "questions/valid-parenthesis-string.json"
    },
    {
      "id": "candy",
      "number": 19,
      "title": "Candy",
      "difficulty": "Hard",
      "categories": [
        "Array",
        "Greedy"
      ],
      "file": "questions/candy.json"
    },
    {
      "id": "boats-to-save-people",
      "number": 17,
      "title": "Boats to Save People",
      "difficulty": "Medium",
      "categories": [
        "Array",
        "Two Pointers",
        "Greedy",
        "Sorting"
      ],
      "file": "questions/boats-to-save-people.json"
    },
    {
      "id": "minimum-interval-to-include-each-query",
      "number": 116,
      "title": "Minimum Interval to Include Each Query",
      "difficulty": "Hard",
      "categories": [
        "Array",
        "Binary Search",
        "Heap / Priority Queue",
        "Sorting",
        "Intervals"
      ],
      "file": "questions/minimum-interval-to-include-each-query.json"
    },
    {
      "id": "single-number",
      "number": 166,
      "title": "Single Number",
      "difficulty": "Easy",
      "categories": [
        "Array",
        "Bit Manipulation"
      ],
      "file": "questions/single-number.json"
    },
    {
      "id": "single-number-ii",
      "number": 167,
      "title": "Single Number II",
      "difficulty": "Medium",
      "categories": [
        "Array",
        "Bit Manipulation"
      ],
      "file": "questions/single-number-ii.json"
    },
    {
      "id": "number-of-1-bits",
      "number": 126,
      "title": "Number of 1 Bits",
      "difficulty": "Easy",
      "categories": [
        "Bit Manipulation"
      ],
      "file": "questions/number-of-1-bits.json"
    },
    {
      "id": "counting-bits",
      "number": 37,
      "title": "Counting Bits",
      "difficulty": "Easy",
      "categories": [
        "Bit Manipulation",
        "Dynamic Programming"
      ],
      "file": "questions/counting-bits.json"
    },
    {
      "id": "reverse-bits",
      "number": 152,
      "title": "Reverse Bits",
      "difficulty": "Easy",
      "categories": [
        "Bit Manipulation"
      ],
      "file": "questions/reverse-bits.json"
    },
    {
      "id": "missing-number",
      "number": 120,
      "title": "Missing Number",
      "difficulty": "Easy",
      "categories": [
        "Array",
        "Bit Manipulation",
        "Math"
      ],
      "file": "questions/missing-number.json"
    },
    {
      "id": "sum-of-two-integers",
      "number": 176,
      "title": "Sum of Two Integers",
      "difficulty": "Medium",
      "categories": [
        "Bit Manipulation",
        "Math"
      ],
      "file": "questions/sum-of-two-integers.json"
    },
    {
      "id": "bitwise-and-of-numbers-range",
      "number": 16,
      "title": "Bitwise AND of Numbers Range",
      "difficulty": "Medium",
      "categories": [
        "Bit Manipulation"
      ],
      "file": "questions/bitwise-and-of-numbers-range.json"
    },
    {
      "id": "hamming-distance",
      "number": 65,
      "title": "Hamming Distance",
      "difficulty": "Easy",
      "categories": [
        "Bit Manipulation"
      ],
      "file": "questions/hamming-distance.json"
    },
    {
      "id": "power-of-two",
      "number": 142,
      "title": "Power of Two",
      "difficulty": "Easy",
      "categories": [
        "Bit Manipulation",
        "Math"
      ],
      "file": "questions/power-of-two.json"
    },
    {
      "id": "happy-number",
      "number": 67,
      "title": "Happy Number",
      "difficulty": "Easy",
      "categories": [
        "Math",
        "Hash Table",
        "Two Pointers"
      ],
      "file": "questions/happy-number.json"
    },
    {
      "id": "plus-one",
      "number": 140,
      "title": "Plus One",
      "difficulty": "Easy",
      "categories": [
        "Array",
        "Math"
      ],
      "file": "questions/plus-one.json"
    },
    {
      "id": "pow-x-n",
      "number": 141,
      "title": "Pow(x, n)",
      "difficulty": "Medium",
      "categories": [
        "Math",
        "Recursion"
      ],
      "file": "questions/pow-x-n.json"
    },
    {
      "id": "sqrt-x",
      "number": 170,
      "title": "Sqrt(x)",
      "difficulty": "Easy",
      "categories": [
        "Math",
        "Binary Search"
      ],
      "file": "questions/sqrt-x.json"
    },
    {
      "id": "fizz-buzz",
      "number": 59,
      "title": "Fizz Buzz",
      "difficulty": "Easy",
      "categories": [
        "Math",
        "String"
      ],
      "file": "questions/fizz-buzz.json"
    },
    {
      "id": "roman-to-integer",
      "number": 156,
      "title": "Roman to Integer",
      "difficulty": "Easy",
      "categories": [
        "Hash Table",
        "Math",
        "String"
      ],
      "file": "questions/roman-to-integer.json"
    },
    {
      "id": "integer-to-roman",
      "number": 73,
      "title": "Integer to Roman",
      "difficulty": "Medium",
      "categories": [
        "Hash Table",
        "Math",
        "String"
      ],
      "file": "questions/integer-to-roman.json"
    },
    {
      "id": "multiply-strings",
      "number": 122,
      "title": "Multiply Strings",
      "difficulty": "Medium",
      "categories": [
        "Math",
        "String",
        "Simulation"
      ],
      "file": "questions/multiply-strings.json"
    },
    {
      "id": "palindrome-number",
      "number": 131,
      "title": "Palindrome Number",
      "difficulty": "Easy",
      "categories": [
        "Math"
      ],
      "file": "questions/palindrome-number.json"
    },
    {
      "id": "add-binary",
      "number": 2,
      "title": "Add Binary",
      "difficulty": "Easy",
      "categories": [
        "Math",
        "String",
        "Bit Manipulation"
      ],
      "file": "questions/add-binary.json"
    },
    {
      "id": "excel-sheet-column-number",
      "number": 51,
      "title": "Excel Sheet Column Number",
      "difficulty": "Easy",
      "categories": [
        "Math",
        "String"
      ],
      "file": "questions/excel-sheet-column-number.json"
    },
    {
      "id": "factorial-trailing-zeroes",
      "number": 52,
      "title": "Factorial Trailing Zeroes",
      "difficulty": "Medium",
      "categories": [
        "Math"
      ],
      "file": "questions/factorial-trailing-zeroes.json"
    },
    {
      "id": "count-primes",
      "number": 36,
      "title": "Count Primes",
      "difficulty": "Medium",
      "categories": [
        "Math"
      ],
      "file": "questions/count-primes.json"
    },
    {
      "id": "divide-two-integers",
      "number": 47,
      "title": "Divide Two Integers",
      "difficulty": "Medium",
      "categories": [
        "Math",
        "Bit Manipulation"
      ],
      "file": "questions/divide-two-integers.json"
    },
    {
      "id": "reverse-integer",
      "number": 153,
      "title": "Reverse Integer",
      "difficulty": "Medium",
      "categories": [
        "Math"
      ],
      "file": "questions/reverse-integer.json"
    },
    {
      "id": "lfu-cache",
      "number": 88,
      "title": "LFU Cache",
      "difficulty": "Hard",
      "categories": [
        "Hash Table",
        "Linked List",
        "Design"
      ],
      "file": "questions/lfu-cache.json"
    },
    {
      "id": "design-twitter",
      "number": 45,
      "title": "Design Twitter",
      "difficulty": "Medium",
      "categories": [
        "Hash Table",
        "Heap / Priority Queue",
        "Design",
        "Linked List"
      ],
      "file": "questions/design-twitter.json"
    },
    {
      "id": "time-based-key-value-store",
      "number": 181,
      "title": "Time Based Key-Value Store",
      "difficulty": "Medium",
      "categories": [
        "Hash Table",
        "String",
        "Binary Search",
        "Design"
      ],
      "file": "questions/time-based-key-value-store.json"
    },
    {
      "id": "insert-delete-getrandom-o1",
      "number": 71,
      "title": "Insert Delete GetRandom O(1)",
      "difficulty": "Medium",
      "categories": [
        "Array",
        "Hash Table",
        "Math",
        "Design"
      ],
      "file": "questions/insert-delete-getrandom-o1.json"
    },
    {
      "id": "design-hit-counter",
      "number": 44,
      "title": "Design Hit Counter",
      "difficulty": "Medium",
      "categories": [
        "Queue",
        "Design",
        "Binary Search"
      ],
      "file": "questions/design-hit-counter.json"
    },
    {
      "id": "design-circular-queue",
      "number": 43,
      "title": "Design Circular Queue",
      "difficulty": "Medium",
      "categories": [
        "Array",
        "Queue",
        "Design",
        "Linked List"
      ],
      "file": "questions/design-circular-queue.json"
    },
    {
      "id": "valid-sudoku",
      "number": 192,
      "title": "Valid Sudoku",
      "difficulty": "Medium",
      "categories": [
        "Array",
        "Hash Table",
        "Matrix"
      ],
      "file": "questions/valid-sudoku.json"
    },
    {
      "id": "spiral-matrix",
      "number": 169,
      "title": "Spiral Matrix",
      "difficulty": "Medium",
      "categories": [
        "Array",
        "Matrix",
        "Simulation"
      ],
      "file": "questions/spiral-matrix.json"
    },
    {
      "id": "rotate-image",
      "number": 158,
      "title": "Rotate Image",
      "difficulty": "Medium",
      "categories": [
        "Array",
        "Matrix",
        "Math"
      ],
      "file": "questions/rotate-image.json"
    },
    {
      "id": "game-of-life",
      "number": 60,
      "title": "Game of Life",
      "difficulty": "Medium",
      "categories": [
        "Array",
        "Matrix",
        "Simulation"
      ],
      "file": "questions/game-of-life.json"
    },
    {
      "id": "first-missing-positive",
      "number": 58,
      "title": "First Missing Positive",
      "difficulty": "Hard",
      "categories": [
        "Array",
        "Hash Table"
      ],
      "file": "questions/first-missing-positive.json"
    },
    {
      "id": "find-the-duplicate-number",
      "number": 56,
      "title": "Find the Duplicate Number",
      "difficulty": "Medium",
      "categories": [
        "Array",
        "Two Pointers",
        "Binary Search",
        "Bit Manipulation"
      ],
      "file": "questions/find-the-duplicate-number.json"
    },
    {
      "id": "majority-element",
      "number": 102,
      "title": "Majority Element",
      "difficulty": "Easy",
      "categories": [
        "Array",
        "Hash Table",
        "Divide & Conquer",
        "Sorting"
      ],
      "file": "questions/majority-element.json"
    },
    {
      "id": "rotate-array",
      "number": 157,
      "title": "Rotate Array",
      "difficulty": "Medium",
      "categories": [
        "Array",
        "Math",
        "Two Pointers"
      ],
      "file": "questions/rotate-array.json"
    },
    {
      "id": "contains-duplicate-ii",
      "number": 32,
      "title": "Contains Duplicate II",
      "difficulty": "Easy",
      "categories": [
        "Array",
        "Hash Table",
        "Sliding Window"
      ],
      "file": "questions/contains-duplicate-ii.json"
    },
    {
      "id": "find-all-anagrams-in-a-string",
      "number": 53,
      "title": "Find All Anagrams in a String",
      "difficulty": "Medium",
      "categories": [
        "String",
        "Hash Table",
        "Sliding Window"
      ],
      "file": "questions/find-all-anagrams-in-a-string.json"
    },
    {
      "id": "string-to-integer-atoi",
      "number": 172,
      "title": "String to Integer (atoi)",
      "difficulty": "Medium",
      "categories": [
        "String",
        "Math"
      ],
      "file": "questions/string-to-integer-atoi.json"
    },
    {
      "id": "isomorphic-strings",
      "number": 76,
      "title": "Isomorphic Strings",
      "difficulty": "Easy",
      "categories": [
        "String",
        "Hash Table"
      ],
      "file": "questions/isomorphic-strings.json"
    },
    {
      "id": "ransom-note",
      "number": 144,
      "title": "Ransom Note",
      "difficulty": "Easy",
      "categories": [
        "String",
        "Hash Table",
        "Counting"
      ],
      "file": "questions/ransom-note.json"
    },
    {
      "id": "length-of-last-word",
      "number": 86,
      "title": "Length of Last Word",
      "difficulty": "Easy",
      "categories": [
        "String"
      ],
      "file": "questions/length-of-last-word.json"
    },
    {
      "id": "longest-common-prefix",
      "number": 91,
      "title": "Longest Common Prefix",
      "difficulty": "Easy",
      "categories": [
        "String",
        "Trie"
      ],
      "file": "questions/longest-common-prefix.json"
    },
    {
      "id": "zigzag-conversion",
      "number": 200,
      "title": "Zigzag Conversion",
      "difficulty": "Medium",
      "categories": [
        "String"
      ],
      "file": "questions/zigzag-conversion.json"
    },
    {
      "id": "find-the-index-of-the-first-occurrence-in-a-string",
      "number": 57,
      "title": "Find the Index of the First Occurrence in a String",
      "difficulty": "Easy",
      "categories": [
        "String",
        "Two Pointers"
      ],
      "file": "questions/find-the-index-of-the-first-occurrence-in-a-string.json"
    },
    {
      "id": "word-pattern",
      "number": 197,
      "title": "Word Pattern",
      "difficulty": "Easy",
      "categories": [
        "String",
        "Hash Table"
      ],
      "file": "questions/word-pattern.json"
    },
    {
      "id": "rotate-string",
      "number": 159,
      "title": "Rotate String",
      "difficulty": "Easy",
      "categories": [
        "String",
        "String Matching"
      ],
      "file": "questions/rotate-string.json"
    }
  ]
}
